pypi_test/__init__.py
pypi_test/pypi_test.py
pypi_test_nchinchi-1.0.5.dist-info/METADATA
pypi_test_nchinchi-1.0.5.dist-info/WHEEL
pypi_test_nchinchi-1.0.5.dist-info/top_level.txt
pypi_test_nchinchi-1.0.5.dist-info/RECORD
