Metadata-Version: 2.1
Name: pypi-test-nchinchi
Version: 1.0.5
Summary: PyPI upload test
Home-page: UNKNOWN
Author: nchikun
Author-email: donkonchi@gmail.com
License: MIT
Keywords: pypi_test
Platform: UNKNOWN
Classifier: License :: OSI Approved :: MIT License
Classifier: Programming Language :: Python :: 3.6
